mdof/__init__.py
mdof/__main__.py
mdof/chrystals_fft.py
mdof/construct.py
mdof/evolve.py
mdof/influence.py
mdof/macro.py
mdof/markov.py
mdof/modal.py
mdof/numerics.py
mdof/prediction.py
mdof/process.py
mdof/realize.py
mdof/simulate.py
mdof/system.py
mdof/transform.py
mdof/units.py
mdof/validation.py
mdof/experimental/stochastic.py
mdof/experimental/util.py
mdof/utilities/__init__.py
mdof/utilities/config.py
mdof/utilities/printing.py
mdof/utilities/testing.py
mdof-0.0.22.dist-info/LICENSE.txt
mdof-0.0.22.dist-info/METADATA
mdof-0.0.22.dist-info/WHEEL
mdof-0.0.22.dist-info/entry_points.txt
mdof-0.0.22.dist-info/top_level.txt
mdof-0.0.22.dist-info/RECORD
